wx_crypt/WXBizMsgCrypt3.py
wx_crypt/__init__.py
wx_crypt/channel.py
wx_crypt/ierror.py
wx_crypt-0.0.2.dist-info/METADATA
wx_crypt-0.0.2.dist-info/WHEEL
wx_crypt-0.0.2.dist-info/RECORD
